odoo/addons/sale_timesheet_timeline/README.rst
odoo/addons/sale_timesheet_timeline/__init__.py
odoo/addons/sale_timesheet_timeline/__manifest__.py
odoo/addons/sale_timesheet_timeline/i18n/es.po
odoo/addons/sale_timesheet_timeline/i18n/it.po
odoo/addons/sale_timesheet_timeline/i18n/sale_timesheet_timeline.pot
odoo/addons/sale_timesheet_timeline/models/__init__.py
odoo/addons/sale_timesheet_timeline/models/sale_order.py
odoo/addons/sale_timesheet_timeline/readme/CONTRIBUTORS.md
odoo/addons/sale_timesheet_timeline/readme/DESCRIPTION.md
odoo/addons/sale_timesheet_timeline/readme/ROADMAP.md
odoo/addons/sale_timesheet_timeline/readme/USAGE.md
odoo/addons/sale_timesheet_timeline/static/description/icon.png
odoo/addons/sale_timesheet_timeline/static/description/index.html
odoo/addons/sale_timesheet_timeline/tests/__init__.py
odoo/addons/sale_timesheet_timeline/tests/test_sale_timesheet_timeline.py
odoo/addons/sale_timesheet_timeline/views/sale_order_views.xml
odoo/addons/sale_timesheet_timeline/views/sale_portal_templates.xml
odoo_addon_sale_timesheet_timeline-18.0.1.0.0.2.dist-info/METADATA
odoo_addon_sale_timesheet_timeline-18.0.1.0.0.2.dist-info/WHEEL
odoo_addon_sale_timesheet_timeline-18.0.1.0.0.2.dist-info/top_level.txt
odoo_addon_sale_timesheet_timeline-18.0.1.0.0.2.dist-info/RECORD
